{
  "address": "0x03e29e82864f160e162482670ec2fd8f5c2f4a4f",
  "type": "ERC721",
  "name": "After Life",
  "tokenCount": "4",
  "uri": "ipfs://QmaUjE1XtwsmKSRGedR6ZnJc136sGiLowPP5Cg2AY8rtwc/metadata.json",
  "metadata": {
    "image": "ipfs://Qmdk8Xebxuqgie8WhhjAbcmwtfr1SbLrSJzR373qbk3jVH/nft.mp4",
    "name": "After Life",
    "description": "After Life\n\n\"The artwork illustrates an alternative universe to our own. In this world, the government and corporations have developed a method for extracting colors from surrounding objects and nature.\n\nThis has made colored objects a tool for manipulation, trade, and propaganda.\"\n\nMusic is exclusively created by @Digital_Moss"
  }
}