{
  "address": "0x071320f43938a0120569b99c266e42e0589f4a85",
  "type": "ERC721",
  "name": "Project CFL",
  "tokenCount": "2",
  "uri": "ipfs://QmZxm1XpyUGeMTB62MCibsFmvLvRnbUXrTEoMSYS2AL2CL/metadata.json",
  "metadata": {
    "name": "Through the chaos",
    "description": "\"Words are not needed here.\n\nAll I require is a single touch, and all of you will gush to me like the great ocean waves.\n\nYour past, your present, your dreams, your secrets, your worries, I can see it vividly before me.\n\nI see what you require of me, and I can, indeed, help you fulfill it.\n\nNow, are you prepared to make our contract binding?\"",
    "image": "ipfs://QmPHR2F47W3sPgnRfGL5nvy4LB3jjwnX5TdtGP7Ue9vaYD/nft.png"
  }
}