{
  "address": "0x0bb7bf76116d56fa3a1bb3b3d0429cad6025f93a",
  "type": "ERC721",
  "name": "BOOF 1987",
  "tokenCount": "1",
  "uri": "ipfs://Qme93dFT4QDCjaW8EsNt5RQ5PiheQgsbpx39yZbnz8d8Bv/metadata.json",
  "metadata": {
    "name": "BUDDHA ON THA BLOCK",
    "description": "When it fails, religion is a good place to start.\n\n\nNot everyone will understand what I am about at first, but eventually, they will come around when they see the magic I’ve created and the waves.",
    "image": "ipfs://QmSzAC7NmhsqVqYh11dLEhc7FA4ekwJdsNeqtkChjekCdr/nft.jpg"
  }
}