{
  "address": "0x0eb8f962f4cdaff55c9b870422a9a1c1bc0c0414",
  "type": "ERC721",
  "name": "Naran",
  "tokenCount": "1",
  "uri": "ipfs://QmZFA2xtqQkKiRVvJcuoKvfy3oQ5Hqu2on7FkYdzq6f4gw/metadata.json",
  "metadata": {
    "name": "BURWAI",
    "description": "\" I always chase the light \"\n\nThis valley is located in the Naran Valley and near the famous Lake Saiful Muluk on the road which connects the KPK with Gilgit-Baltistan Babusar Pass. \n\nBody  : Nikon D850\nLens  : Nikon 70-200mm F4\nCamera Settings : ISO- 100, 1200 Sec , F9\nDimension : 4482*2521\nLocation : Naran , Pakistan",
    "image": "ipfs://QmcG8ArE9WTJ44PMPbQwaxQCgtmSUxHLSNR5nrhtnJiXaq/nft.jpg"
  }
}