{
  "address": "0x14ce0c690dc678fb3be3f7df7a6e478af4ab6ec0",
  "type": "ERC721",
  "name": "The Eccentric Billionaire Collection",
  "tokenCount": "4",
  "uri": "ipfs://QmNmYDRzzzW3Y4R2W6WFy2rHCBzCx81ohwhzoV6AL4XUdC/metadata.json",
  "metadata": {
    "name": "Beave Jobs",
    "description": "Each carefully crafted and detail-oriented piece of collectable 1/1 graphic art in THE ECCENTRIC BILLIONAIRES COLLECTION derives it's inspiration from the captivating and over-indulgent life of some of the world's richest individuals. \n-------\nEACH piece has a number of easter eggs hidden throughout!\n-------\nThis is an ongoing collection of ONLY 1/1.\n-------\n\nBEAVE JOBS depicts the eccentricities and style of the late, great Steve Jobs.  \n-------\nCreated by: Ally Anderson (teh4lly4nderson)",
    "image": "ipfs://QmRVa4xu4c9LFnn9A6DzTapR9udjFtZht5gKWj5JqLrAxe/nft.png"
  }
}