{
  "address": "0x1585cff683988a0235090410a3b3f37eb699e612",
  "type": "ERC1155",
  "name": "Good Morning Pepe Editions",
  "tokenCount": "6",
  "uri": "https://arweave.net/URt29wt1YeuiPteHbQiBWeRGkcIKqVZioYohf6ML_iw",
  "metadata": {
    "name": "Good Morning Pepe Yellow",
    "created_by": "Justin (TAOJ)",
    "description": "Good Morning Pepes. The perfect duo.\n\nCould be used to burn. Could be used as a token for airdrops. Could be for an allowlist. Could just be art. Good Morning.",
    "image_details": {
      "bytes": 6661580,
      "format": "PNG",
      "sha256": "622a2960b5e634ab314ab894fd232a141ed6ed984ee3dfc95199995eeab8ad41",
      "width": 2048,
      "height": 2048
    },
    "image": "https://arweave.net/5XmRwuqRp9yLVBLY2UV6Kyl0e2ZhVAsqwlJ2M_NTfGg",
    "image_url": "https://arweave.net/5XmRwuqRp9yLVBLY2UV6Kyl0e2ZhVAsqwlJ2M_NTfGg"
  }
}