{
  "address": "0x1b21413f83e30e6a0cc34db920c26f3f349f82b9",
  "type": "ERC721",
  "name": "Bitcoin NFT - Innovative Digital Asset",
  "tokenCount": "2",
  "uri": "http://metadata.bitcoinnftid.org/1-1000000/1.json",
  "metadata": {
    "name": "Bitcoin NFT #1",
    "description": "Bitcoin NFT is an innovative digital asset and a new kind of art. It is a collage of 1,000 unique, one-of-a-kind artworks made by anonymous artists globally. Bitcoin NFT was inspired by Satoshi Nakamoto's original vision of Bitcoin. Bitcoin NFT explores the boundaries of art and cryptocurrency. The Bitcoin NFT Project is a collection of 21,000,000 unique NFTs which correspond to 21,000,000 cryptocurrencies which are stored on the blockchain.",
    "image": "http://metadata.bitcoinnftid.org/1-10000/1.jpg"
  }
}