{
  "address": "0x1f0c6c7007790ef8d17e3f962f9bc0c0a895a2df",
  "type": "ERC721",
  "name": "PERSPECTIVE - tslHGIbDGu",
  "tokenCount": "4",
  "uri": "ipfs://QmQGqPaPhgAkcLPUiqJfzzs2U5td4tUE65ZsHPLsDMJHze/metadata.json",
  "metadata": {
    "name": "Wing",
    "description": "As wing covered with feathers, the elegance of this architecture spans over the visitors, transmitting the wonderful sense of lightness.\n\nPhoto, 6000x6000 - NY, USA\nShot, developed and reworked by the author.",
    "image": "ipfs://QmRBoEtkHrUUBVD48Ck8udPLUrT727XZK7k3ZizTrkFHtH/nft.jpg"
  }
}