{
  "address": "0x2020981139b769f1e97f11e98a573070652bd7da",
  "type": "ERC721",
  "name": "TAROT",
  "tokenCount": "5",
  "uri": "ipfs://QmZvnztZPjTh3LH43prxdqiWoxxT3vRSSKnVHXcKfaaJq6/metadata.json",
  "metadata": {
    "name": "THE FOOL",
    "description": "She is a completely unplanned wanderer who walks around completely unrestrained, not even aware of other cards. The eccentricity of her costume is reminiscent of a clown.\nShe has no obsessions or interests",
    "image": "ipfs://QmUDu8ruabSpecTYUAwh182QxdM9gKsX6jTuJsiutVD8nj/nft.png"
  }
}