{
  "address": "0x445456e1c3cc0e11a0488d8857b080b8ebf9506b",
  "type": "ERC721",
  "name": "NAGAS x HANUMAAN",
  "tokenCount": "1",
  "uri": "ipfs://QmQdGuxfXoBT9XufrUvrPgnMgcRW1uchqNs15jRzvrDhwn/metadata.json",
  "metadata": {
    "name": "NAGAS x HANUMAAN ",
    "description": "This is the art of Thailand that has been redesigned by myself. Mix of Japanese art Feels like a Japanese tattoo\n\nHanuman is The Monkey king of Thai literature. it is an albino monkey. It is very powerful. When the power is manifested, there will be 8 arms, immortal when fighting until near death or defeat. Just the wind blows and it will rise again.\n\nNagas is a Giant serpent in the legend of Buddhism and Thailand. is the god of water live in an underground cave very powerful diamond scales able to transform And it is very sacred to people in the eastern part of Thailand.",
    "image": "ipfs://QmRu9KgoUeVsJE6dpUSi4hqi2KBUtZNLs9fAdwFQpvSFcE/nft.png"
  }
}