{
  "address": "0x4762047cb8154086a040f54cccc9a0abaf7ecf2b",
  "type": "ERC721",
  "name": "SUBLIMINAL HIDDEN DREAMS",
  "tokenCount": "5",
  "uri": "ipfs://QmU8T8NzQE3xgmGh5k4kfx7pQsPsMfVakjHCa3CdQcp5HX/metadata.json",
  "metadata": {
    "name": "#5 WANDER",
    "description": "1. SOME WANDER TO GET LOST, AND SOME WANDER TO FIND THEMSELVES.\n\n2. WANDERING DOES NOT SHOW THAT YOU'RE LOST. IT JUST SAYS YOU LIKE TO EXPLORE\n\n3. NEVER STOP WONDERING, NEVER STOP WANDERING\n\n",
    "image": "ipfs://QmX2hsEaQ9i24JSD5oDMF6FYxvMpf311Ut3rwCGajpTZsv/nft.jpg"
  }
}