{
  "address": "0x558898741e8c3347d1e3ea82f8504d59f56c6dc8",
  "type": "ERC721",
  "name": "Are you an adolescent",
  "tokenCount": "1",
  "uri": "ipfs://QmTPYRC9cWmVr4sQRZh882MdytBffhVMZcmu3kUuz3AuxW/metadata.json",
  "metadata": {
    "name": "stuffy",
    "description": "After a hot and humid day, \"she\" can relax in an empty classroom.\nShe sweats more than most people, so she makes sure no one is around to wipe away the sweat.\nI made sure no one was there and was relaxing when I ran into a classmate.\nWhat will happen to her after this, when she is left in a daze due to a combination of heat and surprise?\n\nI hope you will support me so I can paint the rest of these girls!",
    "image": "ipfs://QmVjzAWQrFAZRUN4mquttK1nhAviEtxydUC1BKs3cTVZEu/nft.png"
  }
}