{
  "address": "0x57b9eebd093234c92a3b86726b7a223c15204bce",
  "type": "ERC721",
  "name": "ThePixelatedApes",
  "tokenCount": "3",
  "uri": "https://the-pixelated-apes.mypinata.cloud/ipfs/QmXSuNHXr9bLYxnMDt9cfykHUNXbPKmyic3jNSiqSYgM7h/1.json",
  "metadata": {
    "name": "The Pixelated Apes #1",
    "description": "The Pixelated Apes NFT collection includes 10,000+1 NFTs with a clear message for every human being. A collection that is building unique Web3 products and an exclusive community",
    "image": "https://the-pixelated-apes.mypinata.cloud/ipfs/Qma4Bn8kT9SSqT5zmtkxKxWgFbjVLVhBk5koRDYQLrs8dG",
    "attributes": {}
  }
}