{
  "address": "0x58efe45a785acc52b3f52cfab7138ce642f4d3eb",
  "type": "ERC721",
  "name": "Inner Exploration",
  "tokenCount": "5",
  "uri": "ipfs://QmQY8Zbr6CjzKziEUZp5QzMWpp2Nu4DWj1JwkdEXsYaB2p/metadata.json",
  "metadata": {
    "name": "[IE5]: Scorching mind",
    "description": "SCORCHING MIND\n\n---\n\n[Inner Exploration]\n \nToday’s society is an imprisoned society in which generations of people are closed-minded. Creativity opens our minds, broadens our perspective, and leads to undiscovered places.\n\nTake a deep breath and look inside. Creativity will follow.",
    "image": "ipfs://QmRAvpvcTLpVfNTGWTg6nvvHcD8xeuuUHUjTvFZtHJhtji/nft.png"
  }
}