{
  "address": "0x5ceb1e4d217e23a8921444eee3e4517558ffb5ce",
  "type": "ERC721",
  "name": "Mask Power  The Journey",
  "tokenCount": "4",
  "uri": "ipfs://QmenZzhsMzQscCPBuFvBT6UFyTqUQanQCPQyYKW7jeUtsq/metadata.json",
  "metadata": {
    "name": "Patience",
    "description": "After we struggle and try our best, there is time for us to sit down and be patient. After that it's time to try again and again.\n\nPatience\n3000 x 4000\nJPG\n400 DPI",
    "image": "ipfs://QmSHiReKycUnhgJ7Sos5ckLvNWCYmqC3C5tJAoBRaZVGyN/nft.jpg"
  }
}