{
  "address": "0x630cf3a8a824673d747f7ef2bef97c225db8645b",
  "type": "ERC721",
  "name": "Crypto Oozies",
  "tokenCount": "1",
  "uri": "ipfs://QmZdA7MNW4FYmzwpyRuzJ7Ndv6Tf2R657f3AH1sktQLP5v/metadata.json",
  "metadata": {
    "name": "Bubbah",
    "description": "Bubbah\nElement : Water\nMood : Whimpy\n\n\"What if the sun shrinks me even more? Am i safe under my moss umbrella? Am i... ? i just want to ....stay away from its pesky rays!\"\n\nIllustration by KrakenInABox\nAnimation by CJXander\nMusic by Alex Raptakis\n\n",
    "image": "ipfs://QmazvVBpftMZnSjMfQro4fsk556CRatuua1mHkJ7BTc2Rc/nft.mp4"
  }
}