{
  "address": "0x6383141bf9cfa8df217901fd55886ca25cd94b4c",
  "type": "ERC721",
  "name": "Collage of My Life",
  "tokenCount": "2",
  "uri": "ipfs://QmcmhRKFW9QuFmC2Y25xV5ibhBX13WGgn55p9LqvihpPpS/metadata.json",
  "metadata": {
    "name": "The pain of Human life ",
    "description": "Please don't be sad, Human cycle has Born, Old, Painful, and Death. Satisfy and Disappoint are normal things happened, therefore, Keep the positive memory of eachother in your own heart forever and go on your life to make it the best.\n.\nNo Collage No life\n.\nSize : 2480 × 3508 px\nResolution : 300 \nCreated by Collage Addict1 (1/1)",
    "image": "ipfs://QmfDLugjnMcrriTiX2XhaMdFQomcjENiQjViK37CSQxFaE/nft.jpg"
  }
}