{
  "address": "0x65dbee2280f6be01852bb0f45f86a3614f0a1155",
  "type": "ERC721",
  "name": "Mundo Animal V2",
  "tokenCount": "1",
  "uri": "ipfs://Qmce4ZVJVKof9B96kFNm51Zx5YcznaHNRe9kVUQt1UY5bL/metadata.json",
  "metadata": {
    "name": "the circle of death",
    "description": "Abstract painting based on an acrylic on canvas  painting I've done a couple of years before. I saw the picture of my painting and had the inspiration for this image.",
    "image": "ipfs://QmQGpgEqF93yhYrPx7SxSJgmUHjYA4qf4S5fYUYz5XSTUU/nft.jpg"
  }
}