{
  "address": "0x6753c87078af9aca3b6680e7ada9dec208fe01a1",
  "type": "ERC721",
  "name": "Late Night Illusions",
  "tokenCount": "3",
  "uri": "ipfs://QmPcqk4GJJX1udtSfhW427ZF88HbFFeabaLoWZMTRM37KT/metadata.json",
  "metadata": {
    "name": "Creator Spirit.",
    "description": "\"Creator Spirit\"\nThe genesis.\nSo after the sadness that in the past consumed that poet, illusions come closer accompanied by the light of the moon and the colors of the ghosts of love, more than simple dreams full of desires of uncertainty and passion.\n\nChristoph.\n",
    "image": "ipfs://QmePfDEhUkxAsX3HHWi2i2encMM2egcrhPNymyTeLeCXfs/nft.jpg"
  }
}