{
  "address": "0x757487a910cae308c59e3ba6f9084928e2a8ba8f",
  "type": "ERC721",
  "name": "Journals From Beyond: The Explorers",
  "tokenCount": "70",
  "uri": "ipfs://QmWG3hAZ3RJRQuXTpXua13rEXAxHWa17Rxq6NRWfYVTVNP/hidden.json",
  "metadata": {
    "name": "The Explorers",
    "description": "This seal contains the birth of a great adventure. Dare to free its bonds and be the main witness of Journals From Beyond: The Explorers. Will you be able to immerse yourself in the mysterious paths that make up its world? Do not hesitate: we forge this story together.",
    "image": "ipfs://QmPxuP9GR4FgkPnmxdqiQHD32R9AUNN2KRh8ZH6WidbE95/hidden.mp4"
  }
}