{
  "address": "0x763994078ece08adc13718a8928cc0d1fc814f6d",
  "type": "ERC721",
  "name": "Reflection of Regime",
  "tokenCount": "2",
  "uri": "ipfs://QmWKHjj7ecPxp4TrWaBwv6gubEzyzM4r3ZGDhNY7vfzLxM/metadata.json",
  "metadata": {
    "name": "Dark Lord Thailand",
    "description": "This artwork must show about the Thailand regime. There is someone who can rule behind the government. It's a dark power to order wrong and right. You can order right or wrong according to your needs. on the suffering of the people\nThis art work is my street art work \n\nTechnique : spray paint and negative view \n\n\n",
    "image": "ipfs://QmV7m8vo9kRV1xuLjf5X9JJPDL7sMpxLmRmeUyMkwCZgq1/nft.mp4"
  }
}