{
  "address": "0x7d487e8e94156bb0647f10d79b0c144d84bb7f0d",
  "type": "ERC721",
  "name": "TokenPocket Batch Sender Souvenir",
  "tokenCount": "55",
  "uri": "ipfs://QmNaZTeUqackyr51T4XUaPYCJXQrSD9uFcJRHjaH9RJGiy",
  "metadata": {
    "name": "TokenPocket Batch Sender Souvenir",
    "description": "Your trustable multi-chain Token BatchSender. Batch Sender Souvenir is a gift for all the users who paid for the TokenPocket Token BatchSender before, and it is also a souvenir that can be used as a Pass Card, the holders can get the rewards of the follow-up products and activities.",
    "image": "ipfs://Qme1EX758y7Ef3SwY2knocWHvnFME4wvcaNxnR9z6uG1Qp"
  }
}