{
  "address": "0x82bedae19d5b1362021f35f8478426c28a3d1c4d",
  "type": "ERC721",
  "name": "Other Doors",
  "tokenCount": "3",
  "uri": "ipfs://QmT28hr6bGncA5KSprBVWC7SVDN3XtjTjPWT2uk2zW6vhx/metadata.json",
  "metadata": {
    "name": "Other Doors I",
    "description": "\"Other Doors\"\n\nstring quartet\n\ngraphical score and production by Krist Wood\n\nkristwood.com ------------------- ⍀Ҟ ⌒ ⬣ ð ▰\n\nMP4 file\nMP3 file\naudio tape\n\n2019",
    "image": "ipfs://QmUKBdY4CLKaUJ6AGwgQhYFcqPMeeMEAgbQ1z7ZrcroZDk/nft.mp4"
  }
}