{
  "address": "0x8239501cc717b18aacbd1b2922aee3762b381cb8",
  "type": "ERC721",
  "name": "threshold",
  "tokenCount": "2",
  "uri": "ipfs://QmexAZUQxiJZABe581uEriF2XrGDHTFdAayWAyrGDJFbDF/metadata.json",
  "metadata": {
    "name": "threshold 01",
    "description": "Neither the entrance nor the exit.\nIt's somewhere with unforeseeable destination.\n\nAnalog Photography x Digital Collage\nDimensions: 3652x5444\nEdition of 1",
    "image": "ipfs://QmX2okbeFJTooAXNa8hy6WqFZUKTgN44hAjPYTN7vmKFC2/nft.jpg"
  }
}