{
  "address": "0x83fca6aaaaea6c6d46cd11872be8b43075ea197d",
  "type": "ERC721",
  "name": "HAIKU #3 shareholder of the song",
  "tokenCount": "10",
  "uri": "https://arweave.net/oHVm6lVgJTov8LcD2qGrrpjO4IxAt9t2CnrOjQed1fk",
  "metadata": {
    "name": "Sol Siete HAIKU #3 Token 1",
    "created_by": "Crypto Música Records",
    "external_url": "https://twitter.com/crypto_musica",
    "description": "Click here to see the unlockables:  https://app.niftykit.com/access/ba747151-8256-44fd-9032-84d889bf49c5\n\nArtWork: Eysar Vargas  \nVoice Over: Sol Siete  \nAnimation: Arnold Travieso\n\nIn order to enjoy the essential benefits of this NFT you must write to cryptomusica.records@gmail.com\n\nHaiku Collection #3  are shares that are awarded to participating holders 3 unlockables that are augmented web3 and musical experiences created by ¨Crypto Musica Records¨:\n\nShareholder: of the song with the participation of up to 15% in remixes if the fragment that belongs to your NFT is used.\n\n* Access: to my Discord channel with token where I hold a monthly event.\n\n* Be a member of my union of voters, and sign deciding the destination of the funds to invest in the singer including them in the multi-sig portfolio.\n\n*Lifetime credits: as sponsors in my next albums and video clips.  \n \nArchive feature linked to the guild and remix contest.\n\nEach item has a different snippet of my voice from the Haiku song and a unique cover art but with the same animation. The NFT is not disclosed at the time of purchase.\n\nAfter purchasing it, the NFT will be revealed (it may take a few hours as it is a manual process at the moment)\n\nWhen the first 4 HAIKU #3 NFTs are sold, we start a HAIKU song remix contest with a prize (where the proceeds from the shares will come from)\n\n\nAbout the art in this collection:  \nDesign: Eysar Vargas  \nPoetry, music and lyrics: Sol Siete  \nAnimation: Arnold the Mischievous\n\nTo increase the rarity of this collection, go to the music video:  \nhttps://www.youtube.com/watch?v=WaF2fFzHPRw",
    "animation_details": {
      "bytes": 61146656,
      "format": "MP4",
      "duration": 24,
      "sha256": "c0913899923a4cb66a16ca6723f0b82dfe50e140bba1e27dc280f685e9fc8a45",
      "width": 1500,
      "height": 1500,
      "codecs": [
        "H.264",
        "AAC"
      ]
    },
    "animation": "https://arweave.net/LylddhfkDb50sUsR-NTjY-JeEbncsRTSELivXeC2ur0",
    "animation_url": "https://arweave.net/LylddhfkDb50sUsR-NTjY-JeEbncsRTSELivXeC2ur0",
    "image_details": {
      "bytes": 1492277,
      "format": "PNG",
      "sha256": "c3da04c63663b4e94fa57d48e43d6aa88dbca4981abf60283044ca70c6d8d6f8",
      "width": 3125,
      "height": 3125
    },
    "image": "https://arweave.net/APV6qYnrPwblRZjQfiwxOfzZkm20jBWJPAHrhczLPIM",
    "image_url": "https://arweave.net/APV6qYnrPwblRZjQfiwxOfzZkm20jBWJPAHrhczLPIM"
  }
}