{
  "address": "0x8c681fcb7a3ddf87f76796a607106cb3bc9262cf",
  "type": "ERC721",
  "name": "COLOR WITCH",
  "tokenCount": "2",
  "uri": "ipfs://QmRvreyVBBgdUeXn9F35uXSW3JM8dH5xuK1PV787bucFCa/metadata.json",
  "metadata": {
    "name": "Color Witch Begins",
    "description": "Color Witch Begins!\n\nThis is the story of a witch to get disappeared colors back in the world!\n\nFor the more story, please visit http://colorwitch.net!",
    "image": "ipfs://QmYsSjKTaWjygjG4NqH4KRcq8mbcTLDPx3EBwqg4Tf7jen/nft.mp4"
  }
}