{
  "address": "0x8f1888cd0818da36398863a1138e7469841ac4d8",
  "type": "ERC721",
  "name": "Filippo Salerni - Dynamic Sculptures",
  "tokenCount": "4",
  "uri": "ipfs://QmRdbA4ukJ6m6Bk5XGmuwRmrzByo6X4AaodpQauXy9wxrx/metadata.json",
  "metadata": {
    "name": "Synthesis of  Materic Dynamism",
    "description": "HyperLab, \nDigital reinterpretation 01 of \n“Filippo Salerni, Synthesis of \nMateric Dynamism”, \n3D animation, \n2023",
    "image": "ipfs://QmTCJUmbzRQxim3m1M6Mf1BYKp3sSaUeqjW8aZu5RxE3md/nft.mp4"
  }
}