{
  "address": "0x92379a8ae68da45903caacc52aa63417a0572ac9",
  "type": "ERC721",
  "name": "Filthy Feminine",
  "tokenCount": "1",
  "uri": "ipfs://QmS7uJJRNss5Gk9fftsQTKxqhsKpEsk8H1WvF3HLi4fD1W/metadata.json",
  "metadata": {
    "name": "A Complex Relationship",
    "description": "The color combination of Calamine Blue, Pyrite Yellow, and Raw Sienna reflecting the emotional state of the complicated relationship between the body and mind. ",
    "image": "ipfs://QmQtEZhCz7rtGCroFRnZKh7GiieZ7iZSuft8ihGUimhLun/nft.png"
  }
}