{
  "address": "0x955a453b480809aa77c38a180adc5a9ee15f6a2e",
  "type": "ERC721",
  "name": "White - 1oabyqPLjU",
  "tokenCount": "3",
  "uri": "ipfs://QmbPC6ApBbm5R72niDWyjG8RZmG9fi7kBaiudckUGxKMnj/metadata.json",
  "metadata": {
    "name": "On the road",
    "description": "A hyena running down the road in the early morning hours.\n\nEdition: 1/1\n\nLocation: Serengeti, Tanzania\n\n\n\n\nLicense: NFT holder is free to use in advertising, display, including virtual galleries, documentaries, and essays by holder of the NFT, as long as creator is credited. \nProvides no rights to create commercial merchandise, commercial distribution, or derivative works. Rights remains with creator.\nMore rights can be requested.",
    "image": "ipfs://Qmf1uN8GovZf8EBq1WToEo7abkAmKhxZtT8L1TT2vhkfc5/nft.jpg"
  }
}