{
  "address": "0x9710b25172dd52b583a58425a4e4b2fbec9a6265",
  "type": "ERC721",
  "name": "CAWAII V2",
  "tokenCount": "2",
  "uri": "ipfs://QmRmjp7i1BHvoA9LCpQd3DCZCMhxtKamcXGUyDu47JMqW1/metadata.json",
  "metadata": {
    "name": "Every time I blink",
    "description": "Hello, my name is Chisato Tatsumi. I created NFT to let everyone in the world know about my work. I usually work with acrylic on canvas. I draw pop and cute girls all the time. I would be happy if I could make you all happy in my cute world!",
    "image": "ipfs://QmQBkiC8xLsB3Eker9dx1KwoPzLHLBEYXGRn4GX5RYpDG2/nft.jpg"
  }
}