{
  "address": "0xa6065f795b05c849ff116a2c8b7c04448fd213b9",
  "type": "ERC721",
  "name": "For The Valiant Soul",
  "tokenCount": "1",
  "uri": "ipfs://QmVsTHP49dfApBX1r5LdewvK5qPuretkF69BF6R29znyui/metadata.json",
  "metadata": {
    "name": "For The Valiant Soul",
    "description": "What men call luck is the prerogative of valiant soul, fealty life pays it's rightful king.\"\nJames Russell Lowell 1844\n\nThis body of work is my first trial at virtual photography, I dream about traveling around the world, photographing and experiencing different cultures, while my journey progresses and that dream seemingly on hold, virtual photography have provided me the opportunity to photograph my muses who are miles away from me.\nAs challenging as it might sound it was really interesting and educative.\nThe brave step towards having an experience of virtual photography birthed this masterpiece.\n\nshot via shuttersapp\n\n\nLicense: Can be used to display privately, or in commercial and non-commercial settings, or in groups with an unlimited number of participants. The license includes unlimited use and display in virtual or physical galleries, documentaries, and essays by the NFT holder. Provides no rights to create commercial merchandise, commercial distribution, or derivative works.",
    "image": "ipfs://QmTfu4K2XLLGCrSar4iBGeDHKXUQSSe6VzSVj331TiUK3j/nft.jpg"
  }
}