{
  "address": "0xb2174890c2c5e54f3212be50f15499df470129c8",
  "type": "ERC1155",
  "name": "MAY CONTAIN ALGORITHM",
  "tokenCount": "1",
  "uri": "https://arweave.net/w4Zw5uKM4xPSl5ZJfjcmFNEFhokTGm_dbiltyMadOp4",
  "metadata": {
    "name": "MAY CONTAIN ALGORITHM",
    "created_by": "WARHODL",
    "description": "GM.. HELLO? \nCAN ANYONE SEE THIS? \n\nOK FINE, I'M GOING PRIVAT3\n\nELON CAN YOU DO SOMETHING? \n\nA homage to the incessant tweets announcing your account is now private, and tweeting about being private, and subsequently tweeting about no longer being private, we see you. This one is for you. Circa 2023 Bear Market. \n\nBurn 48 hours after to unlock this soup can and see what comes out. \n\nTo my existing collectors, I see you. I appreciate you. Please enjoy this airdrop 🥫\n\n–––––\n\nWith Twitter, it wasn't clear what it was. \nThey called it a social network, they called it microblogging, but it was hard to define, because it didn't replace anything. There was this path of discovery with something like that, where over time you figure out what it is.\n\n",
    "image_details": {
      "bytes": 1840570,
      "format": "JPEG",
      "sha256": "dc2109ec6116b92b362f916bfc5b1dbf5e90fdf71efbbce5c7ed48e691664211",
      "width": 1643,
      "height": 2362
    },
    "image": "https://arweave.net/R2NoEH4uwWdgWcUDqiE-xtccnGnX44XBR6HO2i2QiUM",
    "image_url": "https://arweave.net/R2NoEH4uwWdgWcUDqiE-xtccnGnX44XBR6HO2i2QiUM"
  }
}