{
  "address": "0xb8c1b139e5db300acbdd2de0db681b18c6201800",
  "type": "ERC721",
  "name": "seedboys",
  "tokenCount": "8",
  "uri": "ipfs://bafybeiepx7vxmchrrov5mrasklxgfggway7zwm2goi3rsaeajmphsv57ce/1",
  "metadata": {
    "name": "seedboys #1",
    "description": "We’re 20 years old, born in Japan and we are seed stage startup boys. This is our first collection. \"Make something People Want.\" 対戦よろしくお願いします。\n\n---\n\nSatopon's Twitter\nhttps://0z.is/satoya.eth/twitter\n\nTomoki's Twitter\nhttps://0z.is/tomokisun.eth/twitter",
    "image": "ipfs://bafybeig6lq7gx34lu4g3tzp2hiiwbb4hcpf3qacbsn3uaejb2fwj5iadc4"
  }
}