{
  "address": "0xbceabff2ee7dc99989cc0337c0c1889ab3f97967",
  "type": "ERC721",
  "name": "Turbo - Jl720dkcuZ",
  "tokenCount": "10",
  "uri": "ipfs://QmX7fjhszWR6cc9vi5BbsUvFdeEDfZuCAcoHa493vTSQcu/metadata.json",
  "metadata": {
    "name": "The credibility test",
    "description": "The level of performance accuracy of the activity is a curvilinear dependence on the level of motivation. \nAs formulated in the XIX century by psychologists Yerkes and Dodson.\n1280х1280,MP4,Original audio",
    "image": "ipfs://QmeC4TAXdywKLdkboXqKmQ57ACgsPLzoAFKm2w8iMTMcG7/nft.mp4"
  }
}