{
  "address": "0xbd9fae6ab1e3b03a2d10234dd7aa4f0b5f68c1f0",
  "type": "ERC721",
  "name": "Svrite - Ascension",
  "tokenCount": "4",
  "uri": "https://hitpiece.mypinata.cloud/ipfs/QmW6XB6LgAaRUXWwdabn3WCLzy1ksVqGvWcJuFKSRXRs7x",
  "metadata": {
    "image": "https://hitpiece.mypinata.cloud/ipfs/QmYtfcHzrz525J4i6aPDsWQeQ8EdQBYGvXPpFUxWsNtRy6",
    "name": "Ascension #023",
    "description": "Svrite's genesis collection consists of 25 unique tokens, differentiated by color with each featuring the track 'I Hope You Listening', that grant owners access to an exclusive unreleased mixtape, Red Room Studio Tapes, additional exclusive content and access, and the initial buyers a FaceTime meet 'n greet with Svrite.  One lucky collector will receive a golden egg surprise of additional exclusive unreleased tracks and a Ledger Nano S hardware wallet. \nFeatured Song: 'I Hope You Listening'\nPerformed by: Svrite\nWritten by: Svrite\nProduced by:  Two Sides",
    "animation_url": "https://hitpiece.mypinata.cloud/ipfs/QmdMsF3Pz22Nx5JWfgVi8sxnD8utmpiZbHYCXgdbLxcTUr",
    "external_url": "",
    "is_sensitive": true,
    "has_unlockable_content": true
  }
}