{
  "address": "0xc0506043cf38a14c22de6ad51352a73692ca681b",
  "type": "ERC1155",
  "name": "Spesh goes to Hollywood",
  "tokenCount": "1",
  "uri": "https://gateway.arweave.net/7cyyg4HDYld2B7ozXJ784RIj2ZLh-e8vT6C2c58YV9g",
  "metadata": {
    "name": "Spesh goes to Hollywood",
    "description": "Spesh and Iggy cuddling up, appreciating you for all your love and care! Special purple edition of Danny Casale’s limited NFT drop in partnership with #FirstRespondersFirst, CARE, and CAA, exclusively for a lucky handful of CMU holders.",
    "image": "https://gateway.arweave.net/mfRboflcaqKCHuGjY-W-L2KlXevLK5vBoh9d12_PNMI"
  }
}