{
  "address": "0xc2ffc3595a637432c7d175cdeb784069858b9ae6",
  "type": "ERC721",
  "name": "Feeling by Hadi Locoboy",
  "tokenCount": "5",
  "uri": "ipfs://Qme3LT9aFRq4Y33qu2BMowwQLw5nDs2HVVshehnQgwrgWZ/metadata.json",
  "metadata": {
    "name": "FVCK SCAMMERS",
    "description": "I really hate to see people who steal other people's work to be traded. I feel they really don't have a brain to think. they don't understand how someone struggles to make their work. I hope all of you are aware of that.\nThanks.",
    "image": "ipfs://QmcRwUDTXVEXjSErcLsT8ewpcGSXwhL2mCrDGfHj1mimg6/nft.png"
  }
}