{
  "address": "0xc41efd458d2e0b777ac5af1dd1f2b43d41791743",
  "type": "ERC721",
  "name": "Nature Streams",
  "tokenCount": "1",
  "uri": "https://arweave.net/9UL-d-QnwjXsZiBKF_SipbkI6aSE1ZGYpSX0Q_9D3Sg",
  "metadata": {
    "name": "Nature Flow",
    "created_by": "Ronen Tanchum",
    "external_url": "https://www.ronentanchum.art/",
    "description": "Observing flowers in wild nature, and re imagining them in the digital realm by using physical simulations in 0 gravity scenarios led to this body of works. This work series reflects on the intersection of the virtual and the physical realms, slowly shifting between order and chaos, and introduces a vast space with an imaginary meditative flower motion stream.",
    "animation_details": {
      "bytes": 113896554,
      "format": "MP4",
      "duration": 83,
      "sha256": "4b5c009e6d3a2d1c2aee10d3dfb4206e304cfb2c6bb0b62282af8e0dfc0b9532",
      "width": 720,
      "height": 720,
      "codecs": [
        "H.264",
        "AAC"
      ]
    },
    "animation": "https://arweave.net/3D0jIIV-l2rKSEFwlZDjBq4PhUoXYnYYTFA2sg7YWv4",
    "animation_url": "https://arweave.net/3D0jIIV-l2rKSEFwlZDjBq4PhUoXYnYYTFA2sg7YWv4",
    "image_details": {
      "bytes": 3754262,
      "format": "JPEG",
      "sha256": "acc39b5d4f46eb0ba67aa62a442de6a781e844340d6f0d48acfe95a0c1ad645f",
      "width": 2160,
      "height": 2160
    },
    "image": "https://arweave.net/RP0J0Yhb57VUvRMgO2DBmaOLMevKSzTv1jTS2gdKTlg",
    "image_url": "https://arweave.net/RP0J0Yhb57VUvRMgO2DBmaOLMevKSzTv1jTS2gdKTlg"
  }
}