{
  "address": "0xc85629702b3da1d9183b03d68143ceb44a90fb2b",
  "type": "ERC1155",
  "name": "Spinal Foxes Da",
  "tokenCount": "1000",
  "uri": "https://cloudflare-ipfs.com/ipfs/QmYWBvs8BSK2G72ayTn8Hz7jrLNbV9U6KaTsZ7BHLZoiXk",
  "metadata": {
    "name": "Spinal Foxes",
    "description": "The human spine consists of 33 vertebrae, our project consists of 6,000 spinal foxes that will help people rebuild! Let Spinal Fox help others. Visit [Here](https://spinalfoxes.link) to find out more.",
    "image": "https://cloudflare-ipfs.com/ipfs/QmRjSZhR6rAiUn6cp2yM8AjLnzvFyhnJhss1ueyqo31vSn",
    "external_url": "https://spinalfoxes.link"
  }
}