{
  "address": "0xc8b495501b7cf22d062b4a9602ac3f1822af1aae",
  "type": "ERC721",
  "name": "On The Beach V2",
  "tokenCount": "2",
  "uri": "ipfs://QmQXpNQ6WFKqDhQ3BpqzF3Grm6r8qRdxLHTPL5ZgYqZFR5/metadata.json",
  "metadata": {
    "name": "Areia",
    "description": "The sunlight soaking into skin, the breeze is caressing body. There are few feelings as reassuring as the sensation of sand between your toes and fingers, your hips, back, your breast and neck.\n\n''Never stop believing in YOUR dreams. Have courage to live the life YOU want. Work hard, accept challenges and build YOUR castles...one by one...''\n\nSize: 7000 x 6400",
    "image": "ipfs://QmX8borCLjKeXT7K2eQjp2i3xuvk8GjBZMeYDXDFsCCZ7A/nft.jpg"
  }
}