{
  "address": "0xcd47bb53a7c871cc6de2e4aa47fee068e2c687ab",
  "type": "ERC721",
  "name": "Daymare Diary",
  "tokenCount": "2",
  "uri": "ipfs://QmTbsxEmm1L51WZiWSM7Pj8P6maizZvXGsC7fwnEXtzSAT/metadata.json",
  "metadata": {
    "name": "A Summer Scare",
    "description": "Warm and split. A sweet sleep under the summer sun on a sweet noon. Which demons come to visit you and make you watch your broken memories like a third-rate movie. Maybe you wake up scared or you look calmly and glide through an unknown hole.",
    "image": "ipfs://QmTQ7m4347MjkC9dpY7Ws4adjyhfz3XK6M89MQYvKtCGNX/nft.mp4"
  }
}