{
  "address": "0xcd91d86b16ec3bddf0809f67b6dcebaebdff73f0",
  "type": "ERC721",
  "name": "Anarchitecture Tokyo",
  "tokenCount": "1",
  "uri": "ipfs://Qmc1Au7r3HgkpHwRxjeDTWykEwPjboX8ne83f2beKQWvzB/metadata.json",
  "metadata": {
    "name": "Anarchitecture Tokyo, Tower Records v1B",
    "description": "WYSI*not*WYG project\n(What You See Is *NOT* What You Get)\n\nAnarchitecture Tokyo\n\nThis animated photograph is from the series Anarchitecture Tokyo made with digital photography. \n\nThe original photographic series was presented at the Digaital Shoc festival held at Atsuko Barouh Gallery from February 28 to March 29, 2015 in Tokyo, Japan\nCurated by Samson Sylvain\n\nSpecs:\n1080*2048, 25 fps\n\nAnarchitecture is an ongoing photographic series from the WYSI*not*WYG project.\nUsing fragmented images of a city photograph from around the world, the process remakes our urban landscape through digitally processed photos that break down and offer a new version of the reality of our day-to-day urban environment. ",
    "image": "ipfs://QmeCkEB3oAbd7FuCbtSdQnoLxrAQDBk7vhRLEZS1zTZUGV/nft.mp4"
  }
}