{
  "address": "0xd2395444f1b7b261d6feb23c503b0915ddd77502",
  "type": "ERC721",
  "name": "The Stories of Ghahve Khane",
  "tokenCount": "1",
  "uri": "ipfs://QmTEDwfGcfBJLbgxCEt3wBMQWE79wdYh5N35J3fTnTEbvz/metadata.json",
  "metadata": {
    "name": "Forbidden Love ",
    "description": "I call you Love, but ;\nyou are Forbidden.\nI call you Life, but ;\nYou are a Ruin.\nWho knows how your forbidden love will restore my ruined soul.\n\n_saeideart-\n",
    "image": "ipfs://QmfHsvWXH6ag5t5JPJkiU7BGYSyUSNQzXDbZJ4jwasWeWr/nft.jpg"
  }
}