{
  "address": "0xda9204e0550ec0165283894ccbf50c8c49380846",
  "type": "ERC721",
  "name": "Undine V2",
  "tokenCount": "1",
  "uri": "ipfs://QmdJyPcXLyYbo58F9jTmiFwxY8ZqCKdeVfgnKWvfxcTBgj/metadata.json",
  "metadata": {
    "name": "Undine",
    "description": "Undine (from Latin unda — \"wave\") is a mythological humanoid female creature associated with reservoirs, fields and fields. The German-Scandinavian and Baltic analog of the Slavic mermaid, a character of the lower mythology of the peoples of Europe.\n\nUndines are beautiful girls, sometimes with fish tails, who come out of the water and comb their hair, singing and beauty, luring travelers into the depths. They seduce men, because if they give birth to a child from an earthly person, they will be able to find an immortal soul.\n\nLike nymphs and mermaids, undines \"rush over fields\" According to legends, a person who gets a fern flower will be able to look at undines without hindrance, not succumb to their charm, and even enlist their help in field work, since undines can control the weather by sending rains.\n\nThe medieval alchemists called Undines spirits that control the water element",
    "image": "ipfs://QmbeHf3G7YSNqUbLZhwJs2fSa4pMVKTRnQDLSZdLRxLLmU/nft.mp4"
  }
}