{
  "address": "0xdb4fd7efd704c537d7b1f760e5ae2850857a5711",
  "type": "ERC721",
  "name": "ROYAL GRAILS",
  "tokenCount": "1",
  "uri": "ipfs://QmQXfFTVPSVpb9UCLXUNF9LcnNLxuwKdoZNBhd5Cn1e7C7/metadata.json",
  "metadata": {
    "name": "KINGDOM GRAIL",
    "description": "8K/DIGITAL ART\n\nI have painted this Art Piece Heavily Inspired by the famous painting of \"Resurrection of Christ\"\nby Charles de La Fosse (1710) \n\nI have taken 15+ days to complete this piece\n\nI look forward to your support during these difficult times for cryptocurrencies. \n\nI accept private deals and offers.",
    "image": "ipfs://QmXqcwNPs5bCygD64Ar7JxgoWjcKjwU9oJXV47wpxXsegf/nft.jpg"
  }
}