{
  "address": "0xdbfd3d0f4bf3cc3bbb74f237758d5bfdf43a5b28",
  "type": "ERC721",
  "name": "Coping Mechanisms V2",
  "tokenCount": "8",
  "uri": "ipfs://QmUfnReANwAFRxGRC4K1pUSkFiRe6T7eayiRTHrCKVtyBH/metadata.json",
  "metadata": {
    "name": "The Only Way Out is In",
    "description": "To savor the murky reflection of one’s self.\n\nTo swim into nothingness and germinate in its texture.\nTo feel again, breathe back into yourself a new living creature. ",
    "image": "ipfs://QmS8oHXVXny8JSNZNMoEsBey4nCcdrcPGMKs2qTzqhC2qt/nft.jpg"
  }
}