{
  "address": "0xdf65588b9dfe0d0f857eac45fab24cf04ece4637",
  "type": "ERC721",
  "name": "SILHOUETTES",
  "tokenCount": "10",
  "uri": "ipfs://QmRm995j3Ger8S8aaaNif5KTAa2x4wduDLs6saYCvwrdV2/1",
  "metadata": {
    "name": "Society #1 #1/5",
    "description": "Objects and figures that are not fully defined stimulate our imagination and draw us into a story. The mystery makes them appealing, encouraging the viewer to think in order to discover the narrative behind the silhouettes.",
    "image": "https://res.cloudinary.com/nifty-gateway/video/upload/v1685648353/publishers/burcu-yildirim/73262/94350/Society1.mp4",
    "image_hash": "QmTGeT6EMPUjM8UPoCD1p2dMwzm7rvTxRW8WZC5SpUGRYM",
    "background_color": "ffffff",
    "external_url": "https://niftygateway.com/collections/silhouettes/"
  }
}