{
  "address": "0xe0c0b0ac4baf7f74f62d339492dd9ce1f90eceaa",
  "type": "ERC721",
  "name": "alternatives V3",
  "tokenCount": "8",
  "uri": "ipfs://QmXuRHRZEoFGd64FwUDzpRtVWAD3r4J1n6kAoNDgKzTgay/metadata.json",
  "metadata": {
    "name": "compendia",
    "description": "Human forms, as well as other forms, are temporal compendia of intemporal elements.\n\nElemental things exist eternally, but constituted or compounded things, that is, forms, lose in wholeness elemental eternity.\n\nHow tenuous are constituted things! If it is form, it shall die; if it is thin, fluxing, formless, it is eternal.\n\n—From an unpublished essay by A.R. Ammons written in 1950\n\nTrained with Generative Adversarial Networks on of a collection of underwater organisms, reconstructions of underlying patterns and spatial representations of sub-aquatic microclimates.\n\ncompendia 0\nAI\n2022\n\n",
    "image": "ipfs://QmWBP1mHaxvriQxceRYexW2iKs4k3v45naPF3nK5v2ZVt5/nft.mov"
  }
}