{
  "address": "0xe516b5b418deadf71e0a685bf2487b368ab10391",
  "type": "ERC721",
  "name": "Alberto Moreno's Films",
  "tokenCount": "99",
  "uri": "https://shirtum-media.s3.eu-west-1.amazonaws.com/all/items/5/jsons/1.json",
  "metadata": {
    "id": 1,
    "name": "The Golden Submarine #1",
    "description": "Alberto Moreno is proclaimed Europa League champion and explains how he felt when he kicked the penalty.",
    "edition": 1,
    "image": "https://s3-eu-west-1.amazonaws.com/shirtum-media/all/items/5/series/imgs/N002-40871574-77b7-433e-a077-1d7d42c7389b.png",
    "animation_url": "https://s3-eu-west-1.amazonaws.com/shirtum-media/all/items/5/series/videos/N003-40871574-77b7-433e-a077-1d7d42c7389b.mp4"
  }
}