{
  "address": "0xe8eea7a15abc4815e10755f552c358c43ca8fe3c",
  "type": "ERC721",
  "name": "the girl - tSVXlDexUz",
  "tokenCount": "15",
  "uri": "ipfs://QmTJHsf4AzEK6aEnbMgHH4GvAxoTB7CXzEzLYLhh1eDG2f/metadata.json",
  "metadata": {
    "name": "Lonely Gamer",
    "description": "Custom derivative of  LonelyPop #2346 \n\nShe grew up lonely,  playing games alone. \n\nBut with internet and web3, she is no longer lonely anymore because she found new friends from all over the world that share her passion. \n\nWith technology and community, all lonely gamers can now be #LonelyTogether",
    "image": "ipfs://QmQJagX1KemgjGZFpSRaSbZNpiFQi68YmwTYzg7FAzHHiJ/nft.png"
  }
}