{
  "address": "0xfb89998dd74552d65a14bd698de37e8dc5588942",
  "type": "ERC721",
  "name": "3D WORKS - ZMFrJaXJW3",
  "tokenCount": "1",
  "uri": "ipfs://QmWeKiZMh8NwBbRzjB11chrXCudrHTCE6XQzTrVNXSKq39/metadata.json",
  "metadata": {
    "name": "LOVE TOKEN ",
    "description": "LOVE TOKEN; including crypto users and NFT artists-collectors sending love to potential Love Token buyers and your loved ones. \n\nLove Token 999th.\n\nLove token includes every love situation in the world. Such as animal love,nature love, general love, religious love etc.\n\nThat is my first 3D Project in Foundation.\n\nIf you want to continue that project, don't hesitate to support me \n\n1920*1080 MP4\n10 sec.",
    "image": "ipfs://QmbEijMmos1r9DSZHxASQF3jA1bG7WHZErxLhEBkMgkM9b/nft.mp4"
  }
}